<manifest alg="2" build="2015.0.2.310" opt="true" iceEnabled="true" iceMarkupVersion="2" exportTarget="other" domain="TeamSpotifier.com" resolutions="1x,2x" timestamp="1449812060424">
  <folder name="images">
    <file name="appicon.png" crc="152208089" seo="true" ref="index"/>
    <file name="appicon_2x.png" crc="4266588112" seo="true" ref="index"/>
    <file name="downarrow.png" crc="3865413860" seo="true" ref="index"/>
    <file name="downarrow_2x.png" crc="329083818" seo="true" ref="index"/>
    <file name="avaone.jpg" crc="141801685" seo="true" ref="index"/>
    <file name="avaone_2x.jpg" crc="279327328" seo="true" ref="index"/>
    <file name="search.png" crc="498766284" seo="true" ref="index"/>
    <file name="search_2x.png" crc="42928676" seo="true" ref="index"/>
    <file name="add.png" crc="4205728463" seo="true" ref="index"/>
    <file name="add_2x.png" crc="248798508" seo="true" ref="index"/>
  </folder>
  <folder name="css">
    <file name="site_global.css" crc="4052507572"/>
    <file name="index.css" crc="12119554" ref="index"/>
  </folder>
  <folder name="scripts">
    <file name="jquery-1.8.3.min.js" crc="196614522" ref="index"/>
    <file name="museutils.js" crc="275725342" ref="index"/>
    <file name="jquery.watch.js" crc="3999102769" ref="index"/>
    <file name="jquery.scrolleffects.js" crc="206645848" ref="index"/>
    <file name="pie.js" crc="3827607177" ref="index"/>
  </folder>
  <file name="index.html" crc="233441360" seo="true" mt="1449811818851" redirect="true"/>
</manifest>